paginx/__init__.py
paginx/db/__init__.py
paginx/db/chroma.py
paginx/db/postgresql.py
paginx/db/retrievers.py
paginx/graphs/basic_rag.py
paginx/graphs/demo.py
paginx/llm/__init__.py
paginx/llm/llm.py
paginx/main.py
paginx/ner/__init__.py
paginx/ner/extract.py
paginx/ner/models/entities.py
paginx/page_crawler/__init__.py
paginx/page_crawler/crawler.py
paginx/page_crawler/models/site_pages.py
paginx/page_crawler/web_chunker.py
paginx/serve.py
paginx-0.0.27.dist-info/LICENSE
paginx-0.0.27.dist-info/METADATA
paginx-0.0.27.dist-info/WHEEL
paginx-0.0.27.dist-info/RECORD
