Metadata-Version: 2.1
Name: paginx
Version: 0.0.27
Summary: An assistant helping you to index webpages into structured datasets.
License: MIT
Author: Ben Selleslagh
Author-email: ben@dataframe.be
Requires-Python: >=3.12,<3.13
Classifier: License :: OSI Approved :: MIT License
Classifier: Programming Language :: Python :: 3
Classifier: Programming Language :: Python :: 3.12
Requires-Dist: bs4 (>=0.0.2,<0.0.3)
Requires-Dist: chroma (>=0.2.0,<0.3.0)
Requires-Dist: fake-useragent (>=1.5.1,<2.0.0)
Requires-Dist: fastapi (>=0.111.0,<0.112.0)
Requires-Dist: langchain (>=0.2.7,<0.3.0)
Requires-Dist: langchain-anthropic (>=0.1.19,<0.2.0)
Requires-Dist: langchain-chroma (>=0.1.1,<0.2.0)
Requires-Dist: langchain-cohere
Requires-Dist: langchain-community (>=0.2.7,<0.3.0)
Requires-Dist: langchain-ollama (>=0.1.0,<0.2.0)
Requires-Dist: langchain-openai (>=0.1.14,<0.2.0)
Requires-Dist: langchain-postgres (>=0.0.9,<0.0.10)
Requires-Dist: langchain-weaviate (>=0.0.2,<0.0.3)
Requires-Dist: langgraph (>=0.1.6,<0.2.0)
Requires-Dist: langgraph-cli (>=0.1.48,<0.2.0)
Requires-Dist: poppler-utils (>=0.1.0,<0.2.0)
Requires-Dist: protobuf (>=4.21.6,<5.0.0)
Requires-Dist: psycopg-binary (>=3.2.1,<4.0.0)
Requires-Dist: replicate (>=0.25.2,<0.26.0)
Requires-Dist: tiktoken (>=0.7.0,<0.8.0)
Requires-Dist: trafilatura (>=1.9.0,<2.0.0)
Requires-Dist: uvicorn (>=0.30.1,<0.31.0)
Requires-Dist: validators (>=0.28.1,<0.29.0)
